lambda_actor/__init__.py
lambda_actor/actor_driver.py
lambda_actor/actor_executor.py
lambda_actor/actor_starter.py
lambda_actor/clear_sqs.py
lambda_actor/aws/__init__.py
lambda_actor/aws/s3.py
lambda_actor/aws/sqs.py
lambda_actor/types/__init__.py
lambda_actor/types/type_actor_message.py
lambda_actor/types/type_conf.py
lambda_actor/utils/__init__.py
lambda_actor/utils/dateutil.py
lambda_actor-0.5.7.dist-info/METADATA
lambda_actor-0.5.7.dist-info/WHEEL
lambda_actor-0.5.7.dist-info/top_level.txt
lambda_actor-0.5.7.dist-info/RECORD
