Metadata-Version: 2.1
Name: lambda-actor
Version: 0.5.7
Summary: Actor model for aws lambda
Home-page: https://www.rescala.jp
Author: rv
Author-email: yo-maruya@rescala.jp
License: MIT
Keywords: lambda actor model
Platform: UNKNOWN
Requires-Python: >=3.7
Requires-Dist: dataclasses-json
